blockscan/__init__.py
blockscan/blockchains.py
blockscan/exception.py
blockscan/main.py
blockscan/connection/__init__.py
blockscan/connection/async_connection.py
blockscan/connection/base.py
blockscan/connection/sync_connection.py
blockscan/enums/__init__.py
blockscan/enums/actions_enum.py
blockscan/enums/fields_enum.py
blockscan/enums/modules_enum.py
blockscan/enums/tags_enum.py
blockscan/modules/__init__.py
blockscan/modules/accounts.py
blockscan/modules/blocks.py
blockscan/modules/contracts.py
blockscan/modules/gas_tracker.py
blockscan/modules/logs.py
blockscan/modules/module.py
blockscan/modules/proxy.py
blockscan/modules/stats.py
blockscan/modules/tokens.py
blockscan/modules/transactions.py
blockscan/utils/__init__.py
blockscan/utils/conversions.py
blockscan/utils/parsing.py
blockscan/utils/request.py
blockscan/utils/wrapper.py
blockscan_python-1.1.1.dist-info/AUTHORS.rst
blockscan_python-1.1.1.dist-info/LICENSE
blockscan_python-1.1.1.dist-info/METADATA
blockscan_python-1.1.1.dist-info/WHEEL
blockscan_python-1.1.1.dist-info/top_level.txt
blockscan_python-1.1.1.dist-info/RECORD
