Metadata-Version: 2.1
Name: blockscan-python
Version: 1.1.1
Summary: A python api wrapper to access the available enpoints from the blockscan.com ecosystem
Home-page: https://github.com/SpeakinTelnet/blockscan-python
Author: SpeakinTelnet
Author-email: gui.lac@protonmail.com
License: MIT license
Keywords: blockscan-python
Classifier: Development Status :: 4 - Beta
Classifier: Intended Audience :: Developers
Classifier: License :: OSI Approved :: MIT License
Classifier: Natural Language :: English
Classifier: Programming Language :: Python :: 3
Classifier: Programming Language :: Python :: 3.8
Classifier: Programming Language :: Python :: 3.9
Classifier: Programming Language :: Python :: 3.10
Classifier: Topic :: Software Development :: Libraries :: Python Modules
Requires-Python: >=3.8
License-File: LICENSE
License-File: AUTHORS.rst
Requires-Dist: aiohttp
Requires-Dist: requests
Requires-Dist: lru-dict
